directory_structure/__init__.py
directory_structure/tree.py
directory_structure-1.1.2.dist-info/LICENSE
directory_structure-1.1.2.dist-info/METADATA
directory_structure-1.1.2.dist-info/WHEEL
directory_structure-1.1.2.dist-info/top_level.txt
directory_structure-1.1.2.dist-info/RECORD
