Metadata-Version: 2.1
Name: directory-structure
Version: 1.1.2
Summary: Print a directory tree structure in your Python code.
Home-page: https://github.com/gabrielstork/directory-structure
Author: Gabriel Stork
Author-email: storkdeveloper@gmail.com
License: MIT
Keywords: directory structure tree emoji folder file
Platform: UNKNOWN
Classifier: Development Status :: 5 - Production/Stable
Classifier: Programming Language :: Python :: 3
Classifier: License :: OSI Approved :: MIT License
Classifier: Operating System :: OS Independent
Requires-Python: >=3
License-File: LICENSE
Requires-Dist: emoji
